jupyterlite_echo_kernel/__init__.py
jupyterlite_echo_kernel/_version.py
jupyterlite_echo_kernel-0.3.0.data/data/share/jupyter/labextensions/@jupyterlite/echo-kernel/package.json
jupyterlite_echo_kernel-0.3.0.data/data/share/jupyter/labextensions/@jupyterlite/echo-kernel/static/599.b4d6b52772e4a8089582.js
jupyterlite_echo_kernel-0.3.0.data/data/share/jupyter/labextensions/@jupyterlite/echo-kernel/static/728.3ddd4cba52963c170cf5.js
jupyterlite_echo_kernel-0.3.0.data/data/share/jupyter/labextensions/@jupyterlite/echo-kernel/static/87.b736f5b276cc91e17cab.js
jupyterlite_echo_kernel-0.3.0.data/data/share/jupyter/labextensions/@jupyterlite/echo-kernel/static/remoteEntry.03bebbc700391811bdc6.js
jupyterlite_echo_kernel-0.3.0.data/data/share/jupyter/labextensions/@jupyterlite/echo-kernel/static/style.js
jupyterlite_echo_kernel-0.3.0.data/data/share/jupyter/labextensions/@jupyterlite/echo-kernel/static/third-party-licenses.json
jupyterlite_echo_kernel-0.3.0.data/data/share/jupyter/labextensions/@jupyterlite/echo-kernel/install.json
jupyterlite_echo_kernel-0.3.0.dist-info/METADATA
jupyterlite_echo_kernel-0.3.0.dist-info/WHEEL
jupyterlite_echo_kernel-0.3.0.dist-info/licenses/LICENSE
jupyterlite_echo_kernel-0.3.0.dist-info/RECORD
