Metadata-Version: 2.4
Name: jupyterlite_echo_kernel
Version: 0.3.0
Summary: Echo kernel for JupyterLite
Project-URL: Homepage, https://github.com/jupyterlite/echo-kernel
Project-URL: Bug Tracker, https://github.com/jupyterlite/echo-kernel/issues
Project-URL: Repository, https://github.com/jupyterlite/echo-kernel.git
Author: JupyterLite Contributors
License: BSD 3-Clause License
License-File: LICENSE
Keywords: jupyter,jupyterlab,jupyterlab-extension
Classifier: Framework :: Jupyter
Classifier: Framework :: Jupyter :: JupyterLab
Classifier: Framework :: Jupyter :: JupyterLab :: 4
Classifier: Framework :: Jupyter :: JupyterLab :: Extensions
Classifier: Framework :: Jupyter :: JupyterLab :: Extensions :: Prebuilt
Classifier: License :: OSI Approved :: BSD License
Classifier: Programming Language :: Python
Classifier: Programming Language :: Python :: 3
Classifier: Programming Language :: Python :: 3.9
Classifier: Programming Language :: Python :: 3.10
Classifier: Programming Language :: Python :: 3.11
Classifier: Programming Language :: Python :: 3.12
Classifier: Programming Language :: Python :: 3.13
Requires-Python: >=3.9
